MANIFEST.in
setup.py
dexy_user_guide_templates/__init__.py
dexy_user_guide_templates/templates.yaml
dexy_user_guide_templates.egg-info/PKG-INFO
dexy_user_guide_templates.egg-info/SOURCES.txt
dexy_user_guide_templates.egg-info/dependency_links.txt
dexy_user_guide_templates.egg-info/top_level.txt
dexy_user_guide_templates/assertions-template/broken.py
dexy_user_guide_templates/assertions-template/dexy.yaml
dexy_user_guide_templates/assertions-template/docs-with-assertions.md
dexy_user_guide_templates/assertions-template/docs-without-assertions.md
dexy_user_guide_templates/canonical-names-template/dexy-env.json
dexy_user_guide_templates/canonical-names-template/dexy.yaml
dexy_user_guide_templates/canonical-names-template/foo.txt
dexy_user_guide_templates/canonical-names-template/bar/baz.txt
dexy_user_guide_templates/canonical-names-template/bar/bell.txt
dexy_user_guide_templates/custom-names-template/dexy-env.json
dexy_user_guide_templates/custom-names-template/dexy.conf
dexy_user_guide_templates/custom-names-template/dexy.yaml
dexy_user_guide_templates/custom-names-template/foo.txt
dexy_user_guide_templates/custom-names-template/bar/baz.txt
dexy_user_guide_templates/custom-names-template/bar/bell.txt
dexy_user_guide_templates/custom-names-template/baz/1.txt
dexy_user_guide_templates/custom-names-template/baz/2.txt
dexy_user_guide_templates/custom-names-template/baz/3.txt
dexy_user_guide_templates/website-links-template/_home.html
dexy_user_guide_templates/website-links-template/_template.html
dexy_user_guide_templates/website-links-template/dexy.conf
dexy_user_guide_templates/website-links-template/dexy.yaml
dexy_user_guide_templates/website-links-template/index.html
dexy_user_guide_templates/website-links-template/foo/index.html
dexy_user_guide_templates/website-navigation-template/_template.html
dexy_user_guide_templates/website-navigation-template/dexy.conf
dexy_user_guide_templates/website-navigation-template/dexy.yaml
dexy_user_guide_templates/website-navigation-template/index.html
dexy_user_guide_templates/website-navigation-template/foo/index.html
dexy_user_guide_templates/website-navigation-template/foo/bar/index.html
