Metadata-Version: 1.1
Name: dexy-user-guide-templates
Version: 0.0.5
Summary: Templates used in Dexy User Guide
Home-page: http://dexy.it
Author: Ana Nelson
Author-email: ana@ananelson.com
License: UNKNOWN
Platform: UNKNOWN
Classifier: License :: OSI Approved :: MIT License
